logstashLog/__init__.py
logstashLog/logstash_log.py
logstashLogging-0.2.0.dist-info/METADATA
logstashLogging-0.2.0.dist-info/WHEEL
logstashLogging-0.2.0.dist-info/top_level.txt
logstashLogging-0.2.0.dist-info/RECORD
